sentry_secure_source_map/__init__.py
sentry_secure_source_map/middleware.py
django_sentry_secure_source_map-0.2.0.dist-info/LICENSE
django_sentry_secure_source_map-0.2.0.dist-info/WHEEL
django_sentry_secure_source_map-0.2.0.dist-info/METADATA
django_sentry_secure_source_map-0.2.0.dist-info/RECORD
