Metadata-Version: 2.1
Name: django-sentry-secure-source-map
Version: 0.2.0
Summary: A middleware to ensure only Sentry can access source maps
Author-email: Torchbox <tech@torchbox.com>
Requires-Python: >=3.9
Classifier: Environment :: Web Environment
Classifier: Framework :: Django
Classifier: Intended Audience :: Developers
Classifier: License :: OSI Approved :: MIT License
Classifier: Operating System :: OS Independent
Classifier: Programming Language :: Python :: 3.9
Classifier: Programming Language :: Python :: 3.10
Classifier: Programming Language :: Python :: 3.11
Classifier: Programming Language :: Python :: 3.12
Classifier: Programming Language :: Python :: 3.13
Classifier: Programming Language :: Python :: 3
Classifier: Programming Language :: Python
Classifier: Topic :: Internet :: WWW/HTTP
Classifier: Topic :: Software Development
Requires-Dist: Django>=4.2
Requires-Dist: ruff==0.6.9 ; extra == "lint"
Requires-Dist: pytest-cov ; extra == "test"
Requires-Dist: pytest-django ; extra == "test"
Requires-Dist: pytest ; extra == "test"
Project-URL: Home, https://torchbox.com
Provides-Extra: lint
Provides-Extra: test
